Ittigorn/Helper.py
Ittigorn/__init__.py
Ittigorn-0.0.2.dist-info/LICENSE.txt
Ittigorn-0.0.2.dist-info/METADATA
Ittigorn-0.0.2.dist-info/WHEEL
Ittigorn-0.0.2.dist-info/top_level.txt
Ittigorn-0.0.2.dist-info/RECORD
