Metadata-Version: 2.1
Name: Ittigorn
Version: 0.0.2
Summary: My helper classes library
Home-page: https://github.com/ittigorn-tra/Ittigorn
License: UNKNOWN
Platform: UNKNOWN
Classifier: Programming Language :: Python :: 3
Classifier: License :: OSI Approved :: MIT License
Classifier: Operating System :: OS Independent
Requires-Python: >=3.7
Requires-Dist: pandas
